goorm/NanumBarunGothic.ttf
goorm/__init__.py
goorm/cli.py
goorm/color_from_image.py
goorm/query_integral_image.cp36-win_amd64.pyd
goorm/stopwords
goorm/tokenization.py
goorm/wordcloud.py
goorm-0.3.9.0.dist-info/DESCRIPTION.rst
goorm-0.3.9.0.dist-info/LICENSE.txt
goorm-0.3.9.0.dist-info/METADATA
goorm-0.3.9.0.dist-info/RECORD
goorm-0.3.9.0.dist-info/WHEEL
goorm-0.3.9.0.dist-info/metadata.json
goorm-0.3.9.0.dist-info/top_level.txt
