Metadata-Version: 2.0
Name: goorm
Version: 0.3.9.0
Summary: A little word cloud generator wrapper with Korean support
Home-page: https://github.com/koshort/goorm
Author: nyanye
Author-email: iam@nyanye.com
License: MIT
Platform: UNKNOWN
Requires-Dist: eunjeon
Requires-Dist: matplotlib
Requires-Dist: numpy (>=1.6.1)
Requires-Dist: pillow
